mdrnn/__init__.py
mdrnn/__version__.py
mdrnn/_layers/__init__.py
mdrnn/_layers/gru.py
mdrnn/_layers/mdlstm.py
mdrnn/_layers/multi_directional.py
mdrnn/_layers/simple_mdrnn.py
mdrnn/_util/__init__.py
mdrnn/_util/directions.py
mdrnn/_util/grids.py
mdrnn-0.3.0.dist-info/LICENSE
mdrnn-0.3.0.dist-info/METADATA
mdrnn-0.3.0.dist-info/WHEEL
mdrnn-0.3.0.dist-info/top_level.txt
mdrnn-0.3.0.dist-info/RECORD
