Metadata-Version: 2.1
Name: mdrnn
Version: 0.3.0
Summary: Custom Keras layers for implementing multi-dimensional recurrent neural networks (MDRNNs)
Home-page: https://github.com/X-rayLaser/multi-directional-mdrnn
Author: Evgenii Dolotov
Author-email: supernovaprotocol@gmail.com
License: MIT
Platform: UNKNOWN
Classifier: Intended Audience :: Developers
Classifier: Programming Language :: Python :: 3.6
Classifier: License :: OSI Approved :: MIT License
Classifier: Operating System :: OS Independent
Requires-Dist: numpy
Requires-Dist: tensorflow (>=2)
